{"1":[{"t":"In (the) name","r":"bis'mi"},{"t":"(of) Allah","r":"l-lahi"},{"t":"the Most Gracious","r":"l-raḥmāni"},{"t":"the Most Merciful","r":"l-raḥīmi"}],"2":[{"t":"All praises and thanks","r":"al-ḥamdu"},{"t":"(be) to Allah","r":"lillahi"},{"t":"the Lord","r":"rabbi"},{"t":"of the universe","r":"l-ʿālamīna"}],"3":[{"t":"The Most Gracious","r":"al-raḥmāni"},{"t":"the Most Merciful","r":"l-raḥīmi"}],"4":[{"t":"(The) Master","r":"māliki"},{"t":"(of the) Day","r":"yawmi"},{"t":"(of the) Judgment","r":"l-dīni"}],"5":[{"t":"You Alone","r":"iyyāka"},{"t":"we worship","r":"naʿbudu"},{"t":"and You Alone","r":"wa-iyyāka"},{"t":"we ask for help","r":"nastaʿīnu"}],"6":[{"t":"Guide us","r":"ih'dinā"},{"t":"(to) the path","r":"l-ṣirāṭa"},{"t":"the straight","r":"l-mus'taqīma"}],"7":[{"t":"(The) path","r":"ṣirāṭa"},{"t":"(of) those","r":"alladhīna"},{"t":"You have bestowed (Your) Favors","r":"anʿamta"},{"t":"on them","r":"ʿalayhim"},{"t":"not (of)","r":"ghayri"},{"t":"those who earned (Your) wrath","r":"l-maghḍūbi"},{"t":"on themselves","r":"ʿalayhim"},{"t":"and not","r":"walā"},{"t":"(of) those who go astray","r":"l-ḍālīna"}]}